Combinational Circuits/Adder/HalfAdder/HalfAdder.v
module HalfAdder (input A, input B , output reg Sum , output reg Carry);

	always @(*)
	begin
		case ({A,B})
			2'b00:
			begin
				Sum = 0;
				Carry = 0;
			end

			2'b11:
			begin
				Sum = 0;
				Carry = 1;
			end

			default:
			begin
				Sum = 1;
				Carry = 0;
			end
		endcase
	end

endmodule

Combinational Circuits/Adder/Full Adder/1bitadder/1bitadder.v
module onebitadder(A, B, CarryIn, Sum, CarryOut);

	input A;
	input B;
	input CarryIn;

	output Sum;
	output CarryOut;
	wire s1;
	wire c1;
	wire c2;

	HalfAdder ha1 (A, B , s1, c1);
	HalfAdder ha2 (s1, CarryIn, Sum, c2);
	assign CarryOut = (c1 | c2);

endmodule

Combinational Circuits/Adder/Full Adder/1bitadder/1bitadderTB.v
module onebitadderTB();

	reg A;
	reg B;
	reg CarryIn;

	wire Sum;
	wire CarryOut;

	onebitadder DUT (.A(A), .B(B), .CarryIn(CarryIn), .Sum(Sum), .CarryOut(CarryOut));

	task init;
		begin
			A = 0;
			B = 0;
			CarryIn = 0;
		end
	endtask


	initial
	begin
		$monitor($time," A = %b, B= %b, CarryIn = %b, Result = %b%b", A,B,CarryIn,CarryOut,Sum);
		$dumpfile("Onebitadderwaveform.vcd");
		$dumpvars(0, onebitadderTB);
	end


	initial
	begin
		init;
		#5 A = 0; B = 0; CarryIn = 0;
		#5 A = 0; B = 0; CarryIn = 1;
		#5 A = 0; B = 1; CarryIn = 0;
		#5 A = 0; B = 1; CarryIn = 1;
		#5 A = 1; B = 0; CarryIn = 0;
		#5 A = 1; B = 0; CarryIn = 1;
		#5 A = 1; B = 1; CarryIn = 0;
		#5 A = 1; B = 1; CarryIn = 1;
		#5 $finish;
	end
endmodule

Combinational Circuits/Adder/Full Adder/1bitadder/Onebitadderwaveform.vcd
$date
	Mon Apr 27 13:25:57 2020
$end
$version
	Icarus Verilog
$end
$timescale
	1s
$end
$scope module onebitadderTB $end
$var wire 1 ! CarryOut $end
$var wire 1 " Sum $end
$var reg 1 # A $end
$var reg 1 $ B $end
$var reg 1 % CarryIn $end
$scope module DUT $end
$var wire 1 & A $end
$var wire 1 ' B $end
$var wire 1 ( CarryIn $end
$var wire 1 ! CarryOut $end
$var wire 1 " Sum $end
$var wire 1 ) c1 $end
$var wire 1 * c2 $end
$var wire 1 + s1 $end
$scope module ha1 $end
$var wire 1 & A $end
$var wire 1 ' B $end
$var reg 1 , Carry $end
$var reg 1 - Sum $end
$upscope $end
$scope module ha2 $end
$var wire 1 + A $end
$var wire 1 ( B $end
$var reg 1 . Carry $end
$var reg 1 / Sum $end
$upscope $end
$upscope $end
$scope task init $end
$upscope $end
$upscope $end
$enddefinitions $end
#0
$dumpvars
0/
0.
0-
0,
0+
0*
0)
0(
0'
0&
0%
0$
0#
0"
0!
$end
#10
1/
1"
1%
1(
#15
1/
1"
1-
1+
0%
0(
1$
1'
#20
1!
1.
1*
0/
0"
1%
1(
#25
0!
0.
0*
1/
1"
0%
0(
0$
0'
1#
1&
#30
1!
1.
1*
0/
0"
1%
1(
#35
0.
0*
0/
0"
1,
1)
0-
0+
0%
0(
1$
1'
#40
1/
1"
1%
1(
