Combinational Circuits/BasicGates/NorGate/NorGate.v
module NorGate(A, B , Out);
	input A , B ;
	output Out;

	assign Out = ~( A | B );

endmodule

Combinational Circuits/BasicGates/NorGate/NorGateTB.v
module NorGateTB();

	reg A , B;
	wire Out;

	NorGate DUT ( .A(A), .B(B), .Out(Out));

	initial 
		begin
			$dumpfile("Norwaveform.vcd");
			$dumpvars(0 , NorGateTB);
		end

	initial
		begin
			$monitor($time," A = %b, B = %b, Out = %b", A ,B , Out);
			#0 A = 1'b0 ; B = 1'b0 ;
			#5 A = 1'b0 ; B = 1'b1 ;
			#5 A = 1'b1 ; B = 1'b0 ;
			#5 A = 1'b1 ; B = 1'b1 ;
			#5 A = 1'b1 ; B = 1'b0 ;
			#5 A = 1'b0 ; B = 1'b0 ;
			#5 A = 1'b1 ; B = 1'b1 ;
			#5 A = 1'b0 ; B = 1'b1 ;
			#5 $finish ;
		end


endmodule

Combinational Circuits/BasicGates/NorGate/Norwaveform.vcd
$date
	Wed Apr  8 21:14:54 2020
$end
$version
	Icarus Verilog
$end
$timescale
	1s
$end
$scope module NorGateTB $end
$var wire 1 ! Out $end
$var reg 1 " A $end
$var reg 1 # B $end
$scope module DUT $end
$var wire 1 $ A $end
$var wire 1 % B $end
$var wire 1 ! Out $end
$upscope $end
$upscope $end
$enddefinitions $end
#0
$dumpvars
0%
0$
0#
0"
1!
$end
#5
0!
1#
1%
#10
0#
0%
1"
1$
#15
1#
1%
#20
0#
0%
#25
1!
0"
0$
#30
0!
1#
1%
1"
1$
#35
0"
0$
