Combinational Circuits/BasicGates/NandGate/NandGate.v
module NandGate (A, B , Out);

	input A, B ;
	output Out ;

	assign Out = ~(A & B);


endmodule

Combinational Circuits/BasicGates/NandGate/NandGateTB.v
module NandGateTB ();
	reg A , B ;
	wire Out;

	NandGate DUT(.A(A), .B(B), .Out(Out));

	initial 
		begin
			$dumpfile("Nandwaveform.vcd");
			$dumpvars(0, NandGateTB);
		end
	
	initial
		begin
			$monitor($time," A = %b, B =%b, Out = %b ", A , B , Out);
			#0 A = 1'b0 ; B = 1'b0 ;
			#5 A = 1'b0 ; B = 1'b1 ;
			#5 A = 1'b1 ; B = 1'b0 ;
			#5 A = 1'b1 ; B = 1'b1 ;
			#5 A = 1'b0 ; B = 1'b0 ;
			#5 A = 1'b0 ; B = 1'b1 ;
			#5 A = 1'b1 ; B = 1'b0 ;
			#5 A = 1'b1 ; B = 1'b1 ;
			#5 A = 1'b0 ; B = 1'b0 ;
			#5 $finish;
		end
endmodule

Combinational Circuits/BasicGates/NandGate/Nandwaveform.vcd
$date
	Wed Apr  8 21:47:30 2020
$end
$version
	Icarus Verilog
$end
$timescale
	1s
$end
$scope module NandGateTB $end
$var wire 1 ! Out $end
$var reg 1 " A $end
$var reg 1 # B $end
$scope module DUT $end
$var wire 1 $ A $end
$var wire 1 % B $end
$var wire 1 ! Out $end
$upscope $end
$upscope $end
$enddefinitions $end
#0
$dumpvars
0%
0$
0#
0"
1!
$end
#5
1#
1%
#10
0#
0%
1"
1$
#15
0!
1#
1%
#20
1!
0#
0%
0"
0$
#25
1#
1%
#30
0#
0%
1"
1$
#35
0!
1#
1%
#40
1!
0#
0%
0"
0$
