Combinational Circuits/BasicGates/AndGate/4inpAnd/And4inp.v
module And4inp (A , B, C , Out);
	input A , B, C ;
	output Out;

	assign Out = (A & B) & C;

endmodule

Combinational Circuits/BasicGates/AndGate/4inpAnd/AndTB.v
module AndTB();
	reg A, B, C;
	wire Out ;

	And4inp DUT (.A(A), .B(B), .C(C), .Out(Out));

	initial
		begin
			$dumpfile ("Andwaveform.vcd");
			$dumpvars(0 , AndTB);
 		end

	initial
		begin
			$monitor ($time ," A = %b, B = %b , C = %b, Out = %b" , A, B, C, Out);
			#5 A = 1'b0 ; B = 1'b0 ; C = 1'b0;
			#5 A = 1'b0 ; B = 1'b1 ; C = 1'b0;
			#5 A = 1'b1 ; B = 1'b1 ; C = 1'b1;
			#5 A = 1'b1 ; B = 1'b0 ; C = 1'b0;
			#5 A = 1'b1 ; B = 1'b0 ; C = 1'b1;
			#5 A = 1'b1 ; B = 1'b1 ; C = 1'b1;
			#5 A = 1'b0 ; B = 1'b1 ; C = 1'b0;
			#5 A = 1'b0 ; B = 1'b0 ; C = 1'b1;
			#5 A = 1'b1 ; B = 1'b0 ; C = 1'b1;
			#5 A = 1'b1 ; B = 1'b1 ; C = 1'b1;
			#5 $finish ;
		end
endmodule

Combinational Circuits/BasicGates/AndGate/4inpAnd/Andwaveform.vcd
$date
	Tue Apr  7 22:19:52 2020
$end
$version
	Icarus Verilog
$end
$timescale
	1s
$end
$scope module AndTB $end
$var wire 1 ! Out $end
$var reg 1 " A $end
$var reg 1 # B $end
$var reg 1 $ C $end
$scope module DUT $end
$var wire 1 % A $end
$var wire 1 & B $end
$var wire 1 ' C $end
$var wire 1 ! Out $end
$upscope $end
$upscope $end
$enddefinitions $end
#0
$dumpvars
x'
x&
x%
x$
x#
x"
x!
$end
#5
0!
0$
0'
0#
0&
0"
0%
#10
1#
1&
#15
1!
1$
1'
1"
1%
#20
0!
0$
0'
0#
0&
#25
1$
1'
#30
1!
1#
1&
#35
0!
0$
0'
0"
0%
#40
1$
1'
0#
0&
#45
1"
1%
#50
1!
1#
1&
