Combinational Circuits/Paritygenerator/Odd/OddParity.v
module OddParityfourbit (A, parity_bit, Out);

	input [2:0]A;
	integer count = 0;
	output reg[3:0]Out;
	output reg parity_bit;
	integer i;

	always@(A)
		begin
			count = 0;
			for (i = 0; i<=2 ; i = i+1)
			begin
				if (A[i] == 1)
				begin
					count = count + 1 ;
				end
			end
			if ((count % 2) == 0)
			begin
				parity_bit = 1;
				Out = {A , parity_bit};
			end
			else if ((count % 2) != 0)
			begin
				parity_bit = 0;
				Out = {A , parity_bit};
			end

		end
endmodule

Combinational Circuits/Paritygenerator/Odd/OddParityTB.v
module OddParityfourbitTB();
	reg [2:0]A;
	wire parity_bit ;
	wire [3:0]Out ;


	OddParityfourbit DUT( .A(A),.parity_bit(parity_bit), .Out(Out));

	initial
		begin
			$dumpfile ("OddParitywaveform.vcd");
			$dumpvars(0, OddParityfourbitTB);
		end
	initial
		begin
			$monitor ($time, " A[2] = %b, A[1] = %b, A[0] = %b ,Out = %b,  parity_bit  = %b", A[2] , A[1], A[0], Out,  parity_bit);
			#0 A[2] = 1'b0; A[1] = 1'b0 ; A[0] = 1'b0;
			#5 A[2] = 1'b0; A[1] = 1'b0 ; A[0] = 1'b1;
			#5 A[2] = 1'b0; A[1] = 1'b1 ; A[0] = 1'b0;
			#5 A[2] = 1'b0; A[1] = 1'b1 ; A[0] = 1'b1;
			#5 A[2] = 1'b1; A[1] = 1'b0 ; A[0] = 1'b0;
			#5 A[2] = 1'b1; A[1] = 1'b0 ; A[0] = 1'b1;
			#5 A[2] = 1'b1; A[1] = 1'b1 ; A[0] = 1'b0;
			#5 A[2] = 1'b1; A[1] = 1'b1 ; A[0] = 1'b1;
			#5 $finish;



		end
endmodule

Combinational Circuits/Paritygenerator/Odd/OddParitywaveform.vcd
$date
	Thu Apr  9 04:30:06 2020
$end
$version
	Icarus Verilog
$end
$timescale
	1s
$end
$scope module OddParityfourbitTB $end
$var wire 4 ! Out [3:0] $end
$var wire 1 " parity_bit $end
$var reg 3 # A [2:0] $end
$scope module DUT $end
$var wire 3 $ A [2:0] $end
$var reg 4 % Out [3:0] $end
$var integer 32 & count [31:0] $end
$var integer 32 ' i [31:0] $end
$var reg 1 ( parity_bit $end
$upscope $end
$upscope $end
$enddefinitions $end
#0
$dumpvars
1(
b11 '
b0 &
b1 %
b0 $
b0 #
1"
b1 !
$end
#5
b10 %
b10 !
0(
0"
b1 &
b11 '
b1 $
b1 #
#10
b100 %
b100 !
b11 '
b1 &
b10 $
b10 #
#15
b111 %
b111 !
1(
1"
b11 '
b10 &
b11 $
b11 #
#20
b1000 %
b1000 !
0(
0"
b11 '
b1 &
b100 #
b100 $
#25
b1011 %
b1011 !
1(
1"
b11 '
b10 &
b101 $
b101 #
#30
b1101 %
b1101 !
b11 '
b10 &
b110 $
b110 #
#35
b1110 %
b1110 !
0(
0"
b11 '
b11 &
b111 $
b111 #
