Combinational Circuits/Paritychecker/Odd/OddParityCheck.v
module OddParityCheck (A , ParityCheck);

	input [3:0]A;
	output reg ParityCheck;
	integer count = 0;
	integer i = 0;

	always@(A)
		begin
			count = 0;
			for(i = 0; i<4; i = i+1)
			begin
				if (A[i] == 1)
				begin
					count = count + 1;
				end
				else
				begin
					count  = count ;
				end
			end
			if ((count % 2) == 0)
			begin
				ParityCheck = 1;

			end
			else
			begin
				ParityCheck = 0;
			end
		end

endmodule

Combinational Circuits/Paritychecker/Odd/OddParityCheckTB.v
module OddParityCheckTB();

	reg [3:0]A;
	wire ParityCheck;

	OddParityCheck DUT( .A(A), .ParityCheck(ParityCheck));

	initial
		begin
			$dumpfile("OddParityCheckwaveform.vcd");
			$dumpvars(0 , OddParityCheckTB);
		end

	initial
		begin
			$monitor($time ," A = %b , ParityCheck = %b ", A , ParityCheck);
			#0 A = 4'h0;
			#5 A = 4'h1;
			#5 A = 4'h2;
			#5 A = 4'h3;
			#5 A = 4'h4;
			#5 A = 4'h5;
			#5 A = 4'h6;
			#5 A = 4'h7;
			#5 A = 4'h8;
			#5 A = 4'h9;
			#5 A = 4'ha;
			#5 A = 4'hb;
			#5 A = 4'hc;
			#5 A = 4'hd;
			#5 A = 4'he;
			#5 A = 4'hf;
			#5 $finish;
		end
endmodule

Combinational Circuits/Paritychecker/Odd/OddParityCheckwaveform.vcd
$date
	Thu Apr  9 21:58:13 2020
$end
$version
	Icarus Verilog
$end
$timescale
	1s
$end
$scope module OddParityCheckTB $end
$var wire 1 ! ParityCheck $end
$var reg 4 " A [3:0] $end
$scope module DUT $end
$var wire 4 # A [3:0] $end
$var reg 1 $ ParityCheck $end
$var integer 32 % count [31:0] $end
$var integer 32 & i [31:0] $end
$upscope $end
$upscope $end
$enddefinitions $end
#0
$dumpvars
b100 &
b0 %
1$
b0 #
b0 "
1!
$end
#5
0$
0!
b1 %
b100 &
b1 "
b1 #
#10
b100 &
b1 %
b10 "
b10 #
#15
1$
1!
b100 &
b10 %
b11 "
b11 #
#20
0$
0!
b100 &
b1 %
b100 "
b100 #
#25
1$
1!
b100 &
b10 %
b101 "
b101 #
#30
b100 &
b10 %
b110 "
b110 #
#35
0$
0!
b100 &
b11 %
b111 "
b111 #
#40
b100 &
b1 %
b1000 "
b1000 #
#45
1$
1!
b100 &
b10 %
b1001 "
b1001 #
#50
b100 &
b10 %
b1010 "
b1010 #
#55
0$
0!
b100 &
b11 %
b1011 "
b1011 #
#60
1$
1!
b100 &
b10 %
b1100 "
b1100 #
#65
0$
0!
b100 &
b11 %
b1101 "
b1101 #
#70
b100 &
b11 %
b1110 "
b1110 #
#75
1$
1!
b100 &
b100 %
b1111 "
b1111 #
