Sequential/Latches/Dlatch/Dlatch1bit.v
module Dlatchonebit (D, En, Q);

 input D,En;
 
 output reg Q;

	always @(*)
	begin
		if (En == 1)
			Q = D;
	end
endmodule

Sequential/Latches/Dlatch/Dlatch4bit.v
module Dlatchfourbit (D, En, Q);

 input [3:0]D;
 input En;
 
 output [3:0]Q;

	Dlatchonebit dl1 (D[0], En, Q[0]);
	Dlatchonebit dl2 (D[1], En, Q[1]);
	Dlatchonebit dl3 (D[2], En, Q[2]);
	Dlatchonebit dl4 (D[3], En, Q[3]);
endmodule

Sequential/Latches/Dlatch/Dlatch4bitTB.v
module DlatchfourbitTB ();

 reg [3:0]D;
 reg En;
 
 wire [3:0]Q;

	Dlatchfourbit DUT (.D(D),.En(En), .Q(Q));

	initial 
	begin
		$monitor($time," D = %b, En = %b, Q = %b", D,En,Q);
		$dumpfile("Dlatchfourbitwaveform.vcd");
		$dumpvars(0,DlatchfourbitTB);
	end


	task initialize;
		begin
			D = 0;
			En = 1;
		end
	endtask

	initial
	begin
		initialize;
		#5 D = 4'hf; En = 1;

		#5 D = 4'h0; En = 0;
		#5 D = 4'hx; En = 1;

		#5 D = 4'h7; En = 1;
		#5 D = 4'h2; En =1;

		#5 D = 4'b1101; En = 1;
		#5 D = 4'b1110; En = 1;

		#5 D = 4'b0001; En = 0;
		#5 $finish;
	end
endmodule

Sequential/Latches/Dlatch/Dlatchfourbitwaveform.vcd
$date
	Mon May  4 01:56:31 2020
$end
$version
	Icarus Verilog
$end
$timescale
	1s
$end
$scope module DlatchfourbitTB $end
$var wire 4 ! Q [3:0] $end
$var reg 4 " D [3:0] $end
$var reg 1 # En $end
$scope module DUT $end
$var wire 4 $ D [3:0] $end
$var wire 1 % En $end
$var wire 4 & Q [3:0] $end
$scope module dl1 $end
$var wire 1 ' D $end
$var wire 1 % En $end
$var reg 1 ( Q $end
$upscope $end
$scope module dl2 $end
$var wire 1 ) D $end
$var wire 1 % En $end
$var reg 1 * Q $end
$upscope $end
$scope module dl3 $end
$var wire 1 + D $end
$var wire 1 % En $end
$var reg 1 , Q $end
$upscope $end
$scope module dl4 $end
$var wire 1 - D $end
$var wire 1 % En $end
$var reg 1 . Q $end
$upscope $end
$upscope $end
$scope task initialize $end
$upscope $end
$upscope $end
$enddefinitions $end
#0
$dumpvars
0.
0-
0,
0+
0*
0)
0(
0'
b0 &
1%
b0 $
1#
b0 "
b0 !
$end
#5
1(
1*
1,
1.
b1111 !
b1111 &
1'
1)
1+
1-
b1111 "
b1111 $
#10
0'
0)
0+
0-
0#
0%
b0 "
b0 $
#15
x.
x,
x*
x(
bx !
bx &
x'
x)
x+
x-
1#
1%
bx "
bx $
#20
1(
1*
1,
0.
b111 !
b111 &
1'
1)
1+
0-
b111 "
b111 $
#25
0(
0,
b10 !
b10 &
0'
0+
b10 "
b10 $
#30
1(
0*
1,
1.
b1101 !
b1101 &
1'
0)
1+
1-
b1101 "
b1101 $
#35
0(
1*
b1110 !
b1110 &
0'
1)
b1110 "
b1110 $
#40
1'
0)
0+
0-
0#
0%
b1 "
b1 $
