Sequential/Latches/Dlatch/Dlatch1bit.v
module Dlatchonebit (D, En, Q);

 input D,En;
 
 output reg Q;

	always @(*)
	begin
		if (En == 1)
			Q = D;
	end
endmodule

Sequential/Latches/Dlatch/Dlatch1bitTB.v
module DlatchonebitTB ();

 reg D;
 reg En;
 
 wire Q;

	Dlatchonebit DUT (.D(D),.En(En), .Q(Q));

	initial 
	begin
		$monitor($time," D = %b, En = %b, Q = %b", D,En,Q);
		$dumpfile("Dlatchonebitwaveform.vcd");
		$dumpvars(0,DlatchonebitTB);
	end

	task initialize;
		begin
			D = 0;
			En = 0;
		end
	endtask

	initial
	begin
		initialize;
		#5 D = 1; En = 1;

		#5 D = 0; En = 0;
		#5 D = 1'bx; En = 1;

		#5 D = 0; En = 1;

		#5 D = 1; En = 1;
		#5 D = 0; En = 1;

		#5 D = 1'bx; En = 1;

		#5 D = 1; En = 1;
		
		#5 D = 0; En =1;
		#5 $finish;
	end
endmodule

Sequential/Latches/Dlatch/Dlatchonebitwaveform.vcd
$date
	Mon May  4 01:43:00 2020
$end
$version
	Icarus Verilog
$end
$timescale
	1s
$end
$scope module DlatchonebitTB $end
$var wire 1 ! Q $end
$var reg 1 " D $end
$var reg 1 # En $end
$scope module DUT $end
$var wire 1 $ D $end
$var wire 1 % En $end
$var reg 1 & Q $end
$upscope $end
$scope task initialize $end
$upscope $end
$upscope $end
$enddefinitions $end
#0
$dumpvars
x&
0%
0$
0#
0"
x!
$end
#5
1&
1!
1#
1%
1"
1$
#10
0#
0%
0"
0$
#15
x&
x!
1#
1%
x"
x$
#20
0&
0!
0"
0$
#25
1&
1!
1"
1$
#30
0&
0!
0"
0$
#35
x&
x!
x"
x$
#40
1&
1!
1"
1$
#45
0&
0!
0"
0$
