Comparator/8bitcomparator.v
module eightbitcomp (input [7:0]A, input [7:0]B, output reg A_great_B, output reg A_less_B , output reg A_equal_B);

 always @(*)
 	begin
		if (A>B)
		begin
			A_great_B = 1;
			A_equal_B = 0;
			A_less_B  = 0;
		end
		else if (A==B)
		begin
			A_great_B = 0;
			A_equal_B = 1;
			A_less_B  = 0;
		end
		else if (A<B)
		begin
			A_great_B = 0;
			A_equal_B = 0;
			A_less_B  = 1;
		end
		else 
		begin
			A_great_B = 0;
			A_equal_B = 0;
			A_less_B  = 0;
		end
	end
endmodule

Comparator/8bitcomparatorTB.v
module eightbitcompTB ();

 reg [7:0]A;
 reg [7:0]B;
 
 wire A_great_B;
 wire A_equal_B;
 wire A_less_B;
 integer i;
	eightbitcomp DUT (.A(A), .B(B), .A_great_B(A_great_B), .A_equal_B(A_equal_B), .A_less_B(A_less_B));

	initial
	begin
		$monitor($time," A = %d, B = %d, A_great_B = %b, A_ equal_B = %b, A_less_B =%b",A,B,A_great_B,A_equal_B, A_less_B);
		$dumpfile("eightbitcompwaveform.vcd");
		$dumpvars(0, eightbitcompTB);
	end

	task initialize;
		begin
			A = 0;
			B = 0;
		end
	endtask

	task stimulus;
		begin
			for(i = 0; i<10; i=i+1)
			begin 
				#5;
				A= $random;
				B =$random;
			end
		end
	endtask

	initial
	begin
		initialize;
		stimulus;
		#5 $finish;
	end
endmodule

Combinational Circuits/Comparator/eightbitcompwaveform.vcd
$date
	Thu Apr 30 03:28:43 2020
$end
$version
	Icarus Verilog
$end
$timescale
	1s
$end
$scope module eightbitcompTB $end
$var wire 1 ! A_equal_B $end
$var wire 1 " A_great_B $end
$var wire 1 # A_less_B $end
$var reg 8 $ A [7:0] $end
$var reg 8 % B [7:0] $end
$var integer 32 & i [31:0] $end
$scope module DUT $end
$var wire 8 ' A [7:0] $end
$var wire 8 ( B [7:0] $end
$var reg 1 ) A_equal_B $end
$var reg 1 * A_great_B $end
$var reg 1 + A_less_B $end
$upscope $end
$scope task initialize $end
$upscope $end
$scope task stimulus $end
$upscope $end
$upscope $end
$enddefinitions $end
#0
$dumpvars
0+
0*
1)
b0 (
b0 '
b0 &
b0 %
b0 $
0#
0"
1!
$end
#5
1+
1#
0)
0!
b1 &
b10000001 %
b10000001 (
b100100 $
b100100 '
#10
b10 &
b1100011 %
b1100011 (
b1001 $
b1001 '
#15
b11 &
b10001101 %
b10001101 (
b1101 $
b1101 '
#20
0+
0#
1*
1"
b100 &
b10010 %
b10010 (
b1100101 $
b1100101 '
#25
1+
1#
0*
0"
b101 &
b1101 %
b1101 (
b1 $
b1 '
#30
0+
0#
1*
1"
b110 &
b111101 %
b111101 (
b1110110 $
b1110110 '
#35
b111 &
b10001100 %
b10001100 (
b11101101 $
b11101101 '
#40
b1000 &
b11000110 %
b11000110 (
b11111001 $
b11111001 '
#45
b1001 &
b10101010 %
b10101010 (
b11000101 $
b11000101 '
#50
b1010 &
b1110111 %
b1110111 (
b11100101 $
b11100101 '
