Combinational Circuits/Subtractor/HalfSubtractor/halfsub.v
module halfsub (A , B, Diff, Borrow);

	input A;
	input B;
	output reg Diff;
	output reg  Borrow;

	always @(*)
	begin
		case ({A, B})
			2'b00:
			begin
				Diff <= 0;
				Borrow <= 0;
			end
			2'b01:
			begin
				Diff <= 1;
				Borrow <= 1;
			end
			2'b10:
			begin
				Diff <=1;
				Borrow <= 0;
			end
			2'b11:
			begin
				Diff <= 0;
				Borrow <= 0;
			end
			default:
			begin
				Diff <= 0;
				Borrow <=0;
			end

		endcase
	end
endmodule

Combinational Circuits/Subtractor/FullSubtractor/FullSub1bit.v
module onebitfullsub( A, B , BorrowIn, Diff, BorrowOut);
	input A;
	input B;
	input BorrowIn;

	output Diff;
	output BorrowOut;

	wire Diff1;
	wire borrow1, borrow2;

	halfsub hs1 (A, B, Diff1, borrow1);
	halfsub hs2 (Diff1, BorrowIn, Diff, borrow2);
	assign BorrowOut = (borrow1 | borrow2);

endmodule

Combinational Circuits/Subtractor/FullSubtractor/FullSub1bitTB.v
module onebitfullsubTB();

	reg A;
	reg B;
	reg BorrowIn;
	
	wire Diff;
	wire BorrowOut;

	onebitfullsub DUT(.A(A), .B(B), .BorrowIn(BorrowIn), .Diff(Diff), .BorrowOut(BorrowOut));

	task initialize;
		begin
			A = 0;
			B = 0;
			BorrowIn = 0;
		end
	endtask

	initial
	begin
		$monitor($time," A = %b, B = %b, BorrowIn = %b, Diff = %b, BorrowOut = %b", A, B, BorrowIn, Diff, BorrowOut);
		$dumpfile("fullsubwaveform.vcd");
		$dumpvars(0, onebitfullsubTB);	
	end

	initial
	begin
		initialize;
		#5 A = 0; B = 0; BorrowIn = 0;
		#5 A = 0; B = 0; BorrowIn = 1;
		#5 A = 0; B = 1; BorrowIn = 0;
		#5 A = 0; B = 1; BorrowIn = 1;
		#5 A = 1; B = 0; BorrowIn = 0;
		#5 A = 1; B = 0; BorrowIn = 1;
		#5 A = 1; B = 1; BorrowIn = 0;
		#5 A = 1; B = 1; BorrowIn = 1;
		#5 $finish;
	end
endmodule

Combinational Circuits/Subtractor/FullSubtractor/fullsubwaveform.vcd
$date
	Mon Apr 13 21:20:53 2020
$end
$version
	Icarus Verilog
$end
$timescale
	1s
$end
$scope module onebitfullsubTB $end
$var wire 1 ! BorrowOut $end
$var wire 1 " Diff $end
$var reg 1 # A $end
$var reg 1 $ B $end
$var reg 1 % BorrowIn $end
$scope module DUT $end
$var wire 1 & A $end
$var wire 1 ' B $end
$var wire 1 ( BorrowIn $end
$var wire 1 ! BorrowOut $end
$var wire 1 " Diff $end
$var wire 1 ) Diff1 $end
$var wire 1 * borrow1 $end
$var wire 1 + borrow2 $end
$scope module hs1 $end
$var wire 1 & A $end
$var wire 1 ' B $end
$var reg 1 , Borrow $end
$var reg 1 - Diff $end
$upscope $end
$scope module hs2 $end
$var wire 1 ) A $end
$var wire 1 ( B $end
$var reg 1 . Borrow $end
$var reg 1 / Diff $end
$upscope $end
$upscope $end
$scope task initialize $end
$upscope $end
$upscope $end
$enddefinitions $end
#0
$dumpvars
0/
0.
0-
0,
0+
0*
0)
0(
0'
0&
0%
0$
0#
0"
0!
$end
#10
1!
1.
1+
1/
1"
1%
1(
#15
0.
0+
1/
1"
1,
1*
1-
1)
0%
0(
1$
1'
#20
0/
0"
1%
1(
#25
0!
1/
1"
0,
0*
0%
0(
0$
0'
1#
1&
#30
0/
0"
1%
1(
#35
0/
0"
0-
0)
0%
0(
1$
1'
#40
1!
1.
1+
1/
1"
1%
1(
