Combinational Circuits/EncodersAndDecoders/8to3prioritypart2.v
module eighttothreepart2 (code , data);

 input [7:0]data;

 output reg [2:0]code;

	 always @ (*)
	 begin
		case (data)
			8'b00000001 : code = 3'b000;
			8'b00000010 : code = 3'b001;
			8'b00000100 : code = 3'b010;
			8'b00001000 : code = 3'b011;
    			8'b00010000 : code = 3'b100;
			8'b00100000 : code = 3'b101;
			8'b01000000 : code = 3'b110;
			8'b10000000 : code = 3'b111;
			default     : code = 3'bx;
		endcase
	end
endmodule

Combinational Circuits/EncodersAndDecoders/8to3prioritypart2TB.v
module eighttothreepart2TB ();

 reg [7:0]data;

 wire [2:0]code;
 
	eighttothreepart2 DUT (.data(data), .code(code));
	
	initial
	begin
		$monitor($time," data = %b, code =%d",data,code);
		$dumpfile("eighttothreepart2waveform.vcd");
		$dumpvars(0,eighttothreepart2TB);
	end
	
	task initialize;
		begin
			data = 0;
		end
	endtask

	initial
	begin
		initialize;
		#5 data = 8'b00000101; 
		#5 data = 8'b01000000; 
 		#5 data = 8'b10000000; 
 		#5 data = 8'b11111111; 
		#5 data = 8'b00000001;
 		#5 data = 8'b00000100;
 		#5 data = 8'b00000000;
 		#5 data = 8'b01111011;
 		#5 $finish;
	end
endmodule

Combinational Circuits/EncodersAndDecoders/eighttothreepart2waveform.vcd
$date
	Tue May  5 21:53:18 2020
$end
$version
	Icarus Verilog
$end
$timescale
	1s
$end
$scope module eighttothreepart2TB $end
$var wire 3 ! code [2:0] $end
$var reg 8 " data [7:0] $end
$scope module DUT $end
$var wire 8 # data [7:0] $end
$var reg 3 $ code [2:0] $end
$upscope $end
$scope task initialize $end
$upscope $end
$upscope $end
$enddefinitions $end
#0
$dumpvars
bx $
b0 #
b0 "
bx !
$end
#5
b101 "
b101 #
#10
b110 $
b110 !
b1000000 "
b1000000 #
#15
b111 $
b111 !
b10000000 "
b10000000 #
#20
bx $
bx !
b11111111 "
b11111111 #
#25
b0 $
b0 !
b1 "
b1 #
#30
b10 $
b10 !
b100 "
b100 #
#35
bx $
bx !
b0 "
b0 #
#40
b1111011 "
b1111011 #
