Combinational Circuits/EncodersAndDecoders/8to3priority.v
module eighttothreeencoder (code , din);

 input [7:0]din;

 output reg [2:0]code;

	 always @ (*)
	 begin
		if (din[0] == 1)
			code = 3'b000;
		else if(din[1] == 1)
			code = 3'b001;
		else if(din[2] == 1)
			code = 3'b010;
		else if(din[3] == 1)
			code = 3'b011;
		else if(din[4] == 1)
			code = 3'b100;
		else if(din[5] == 1)
			code = 3'b101;
		else if(din[6] == 1)
			code = 3'b110;
		else if(din[7] == 1)
			code = 3'b111;
		else
			code = 3'bx;
	end
endmodule

Combinational Circuits/EncodersAndDecoders/8to3priorityTB.v
module eighttothreeencoderTB ();

 reg [7:0]din;

 wire [2:0]code;
 
	eighttothreeencoder DUT (.din(din), .code(code));
	
	initial
	begin
		$monitor($time," din = %b, code =%b",din,code);
		$dumpfile("eighttothreeencoder.vcd");
		$dumpvars(0,eighttothreeencoderTB);
	end
	
	task initialize;
		begin
			din = 0;
		end
	endtask

	initial
	begin
		initialize;
		#5 din = 8'b11111111; 
		#5 din = 8'b11110000; 
 		#5 din = 8'b00001111; 
 		#5 din = 8'b01000100; 
		#5 din = 8'b10000000;
 		#5 din = 8'b10001000;
 		#5 din = 8'b00000000;
 		#5 din = 8'b00000001;
 		#5 $finish;
	end
endmodule

Combinational Circuits/EncodersAndDecoders/eighttothreeencoder.vcd
$date
	Tue May  5 13:49:29 2020
$end
$version
	Icarus Verilog
$end
$timescale
	1s
$end
$scope module eighttothreeencoderTB $end
$var wire 3 ! code [2:0] $end
$var reg 8 " din [7:0] $end
$scope module DUT $end
$var wire 8 # din [7:0] $end
$var reg 3 $ code [2:0] $end
$upscope $end
$scope task initialize $end
$upscope $end
$upscope $end
$enddefinitions $end
#0
$dumpvars
bx $
b0 #
b0 "
bx !
$end
#5
b0 $
b0 !
b11111111 "
b11111111 #
#10
b100 $
b100 !
b11110000 "
b11110000 #
#15
b0 $
b0 !
b1111 "
b1111 #
#20
b10 $
b10 !
b1000100 "
b1000100 #
#25
b111 $
b111 !
b10000000 "
b10000000 #
#30
b11 $
b11 !
b10001000 "
b10001000 #
#35
bx $
bx !
b0 "
b0 #
#40
b0 $
b0 !
b1 "
b1 #
