Combinational Circuits/Paritygenerator/Even/EvenParity.v
module EvenParityfourbit (A, parity_bit, Out);

	input [2:0]A;
	integer count = 0;
	output reg[3:0]Out;
	output reg parity_bit;
	integer i;

	always@(A)
		begin
			count = 0;
			for (i = 0; i<=2 ; i = i+1)
			begin
				if (A[i] == 1)
				begin
					count = count + 1 ;
				end
			end
			if ((count % 2) == 0)
			begin
				parity_bit = 0;
				Out = {A , parity_bit};
			end
			else if ((count % 2) != 0)
			begin
				parity_bit = 1 ;
				Out = {A , parity_bit};
			end

		end
endmodule

Combinational Circuits/Paritygenerator/Even/EvenParityTB.v
module EvenParityfourbitTB();
	reg [2:0]A;
	wire parity_bit ;
	wire [3:0]Out ;


	EvenParityfourbit DUT( .A(A),.parity_bit(parity_bit), .Out(Out));

	initial
		begin
			$dumpfile ("EvenParitywaveform.vcd");
			$dumpvars(0, EvenParityfourbitTB);
		end
	initial
		begin
			$monitor ($time, " A[0] = %b, A[1] = %b, A[2] = %b, Out = %b, parity_bit  = %b", A[0] , A[1] , A[2], Out,  parity_bit);
			#0 A[2] = 1'b0; A[1] = 1'b0 ; A[0] = 1'b0;
			#5 A[2] = 1'b0; A[1] = 1'b0 ; A[0] = 1'b1;
			#5 A[2] = 1'b0; A[1] = 1'b1 ; A[0] = 1'b0;
			#5 A[2] = 1'b0; A[1] = 1'b1 ; A[0] = 1'b1;
			#5 A[2] = 1'b1; A[1] = 1'b0 ; A[0] = 1'b0;
			#5 A[2] = 1'b1; A[1] = 1'b0 ; A[0] = 1'b1;
			#5 A[2] = 1'b1; A[1] = 1'b1 ; A[0] = 1'b0;
			#5 A[2] = 1'b1; A[1] = 1'b1 ; A[0] = 1'b1;
			#5 $finish;


		end
endmodule

Combinational Circuits/Paritygenerator/Even/EvenParitywaveform.vcd
$date
	Thu Apr  9 04:27:22 2020
$end
$version
	Icarus Verilog
$end
$timescale
	1s
$end
$scope module EvenParityfourbitTB $end
$var wire 4 ! Out [3:0] $end
$var wire 1 " parity_bit $end
$var reg 3 # A [2:0] $end
$scope module DUT $end
$var wire 3 $ A [2:0] $end
$var reg 4 % Out [3:0] $end
$var integer 32 & count [31:0] $end
$var integer 32 ' i [31:0] $end
$var reg 1 ( parity_bit $end
$upscope $end
$upscope $end
$enddefinitions $end
#0
$dumpvars
0(
b11 '
b0 &
b0 %
b0 $
b0 #
0"
b0 !
$end
#5
b11 %
b11 !
1(
1"
b1 &
b11 '
b1 $
b1 #
#10
b101 %
b101 !
b11 '
b1 &
b10 $
b10 #
#15
b110 %
b110 !
0(
0"
b11 '
b10 &
b11 $
b11 #
#20
b1001 %
b1001 !
1(
1"
b11 '
b1 &
b100 #
b100 $
#25
b1010 %
b1010 !
0(
0"
b11 '
b10 &
b101 $
b101 #
#30
b1100 %
b1100 !
b11 '
b10 &
b110 $
b110 #
#35
b1111 %
b1111 !
1(
1"
b11 '
b11 &
b111 $
b111 #
