Combinational Circuits/Paritychecker/Even/EvenParityCheck.v
module EvenParityCheck (A , ParityCheck);
	
	input [3:0]A;
	output reg ParityCheck;
	integer count = 0;
	integer i = 0;

	always@(A)
		begin
			count = 0;
			for(i = 0; i<4; i = i+1)
			begin
				if (A[i] == 1)			
				begin
					count = count + 1; 
				end
				else 
				begin
					count  = count ;
				end
			end
			if ((count % 2) == 0)
			begin
				ParityCheck = 0;
			
			end
			else 
			begin
				ParityCheck = 1;
			end
		end 

endmodule

Combinational Circuits/Paritychecker/Even/EvenParityCheckTB.v
module EvenParityCheckTB();

	reg [3:0]A;
	wire ParityCheck;

	EvenParityCheck DUT( .A(A), .ParityCheck(ParityCheck));

	initial
		begin
			$dumpfile("EvenParityCheckwaveform.vcd");
			$dumpvars(0 , EvenParityCheckTB);
		end

	initial
		begin
			$monitor($time ," A = %b , ParityCheck = %b ", A , ParityCheck);
			#0 A = 4'b0000;
			#5 A = 4'b0001;
			#5 A = 4'b0010;
			#5 A = 4'b0011;
			#5 A = 4'b0100;
			#5 A = 4'b0101;
			#5 A = 4'b0110;
			#5 A = 4'b0111;
			#5 A = 4'b1000;
			#5 A = 4'b1001;
			#5 A = 4'b1010;
			#5 A = 4'b1011;
			#5 A = 4'b1100;
			#5 A = 4'b1101;
			#5 A = 4'b1110;
			#5 A = 4'b1111;
			#5 $finish;
		end
endmodule

Combinational Circuits/Paritychecker/Even/EvenParityCheckwaveform.vcd
$date
	Thu Apr  9 22:01:01 2020
$end
$version
	Icarus Verilog
$end
$timescale
	1s
$end
$scope module EvenParityCheckTB $end
$var wire 1 ! ParityCheck $end
$var reg 4 " A [3:0] $end
$scope module DUT $end
$var wire 4 # A [3:0] $end
$var reg 1 $ ParityCheck $end
$var integer 32 % count [31:0] $end
$var integer 32 & i [31:0] $end
$upscope $end
$upscope $end
$enddefinitions $end
#0
$dumpvars
b100 &
b0 %
0$
b0 #
b0 "
0!
$end
#5
1$
1!
b1 %
b100 &
b1 "
b1 #
#10
b100 &
b1 %
b10 "
b10 #
#15
0$
0!
b100 &
b10 %
b11 "
b11 #
#20
1$
1!
b100 &
b1 %
b100 "
b100 #
#25
0$
0!
b100 &
b10 %
b101 "
b101 #
#30
b100 &
b10 %
b110 "
b110 #
#35
1$
1!
b100 &
b11 %
b111 "
b111 #
#40
b100 &
b1 %
b1000 "
b1000 #
#45
0$
0!
b100 &
b10 %
b1001 "
b1001 #
#50
b100 &
b10 %
b1010 "
b1010 #
#55
1$
1!
b100 &
b11 %
b1011 "
b1011 #
#60
0$
0!
b100 &
b10 %
b1100 "
b1100 #
#65
1$
1!
b100 &
b11 %
b1101 "
b1101 #
#70
b100 &
b11 %
b1110 "
b1110 #
#75
0$
0!
b100 &
b100 %
b1111 "
b1111 #
