Combinational Circuits/Adder/HalfAdder/HalfAdder.v
module HalfAdder (input A, input B , output reg Sum , output reg Carry);

	always @(*)
	begin
		case ({A,B})
			2'b00:
			begin
				Sum = 0;
				Carry = 0;
			end

			2'b11:
			begin
				Sum = 0;
				Carry = 1;
			end

			default:
			begin
				Sum = 1;
				Carry = 0;
			end
		endcase
	end

endmodule

Combinational Circuits/Adder/Full Adder/1bitadder/1bitadder.v
module onebitadder(A, B, CarryIn, Sum, CarryOut);

	input A;
	input B;
	input CarryIn;

	output Sum;
	output CarryOut;
	wire s1;
	wire c1;
	wire c2;

	HalfAdder ha1 (A, B , s1, c1);
	HalfAdder ha2 (s1, CarryIn, Sum, c2);
	assign CarryOut = (c1 | c2);

endmodule

Combinational Circuits/Adder/Full Adder/2bitadder/2bitFullAdder.v
/*module twobitFullAdder(A, B, CarryIn, Sum, CarryOut);
	input [1:0] A;
	input [1:0] B;
	input CarryIn;
	output [1:0] Sum;
	output CarryOut;
	wire [2:0] temp;

	assign temp = A + B + CarryIn;
	assign Sum = temp [1:0];
	assign CarryOut = temp [2];

endmodule*/


/*module twobitFullAdder(A, B, CarryIn, Sum, CarryOut);
	input [1:0] A;
	input [1:0] B;
	input CarryIn;

	output reg[1:0] Sum;
	output reg CarryOut;

	always @(*)
	begin
		case({A , B, CarryIn})
			5'b00000:
			begin
				Sum <= 2'b00;
				CarryOut <= 0;
			end
			5'b00001:
			begin
				Sum <= 2'b10;
				CarryOut <= 0;
			end
			5'b00010:
			begin
				Sum <= 2'b10;
				CarryOut <= 0;
			end
			5'b00011:
			begin
				Sum <= 2'b01;
				CarryOut <= 0;
			end
			5'b00100:
			begin
				Sum <= 2'b10;
				CarryOut <= 0;
			end
			5'b00101:
			begin
				Sum <= 2'b01;
				CarryOut <= 0;
			end
			5'b00110:
			begin
				Sum <= 2'b01;
				CarryOut <= 0;
			end
			5'b00111:
			begin
				Sum <= 2'b11;
				CarryOut <= 0;
			end

			5'b01000:
			begin
				Sum <= 2'b10;
				CarryOut <= 0;
			end
			5'b01001:
			begin
				Sum <= 2'b01;
				CarryOut <= 0;
			end
			5'b01010:
			begin
				Sum <= 2'b01;
				CarryOut <= 0;
			end
			5'b01011:
			begin
				Sum <= 2'b11;
				CarryOut <= 0;
			end
			5'b01100:
			begin
				Sum <= 2'b01;
				CarryOut <= 0;
			end
			5'b01101:
			begin
				Sum <= 2'b11;
				CarryOut <= 0;
			end
			5'b01110:
			begin
				Sum <= 2'b11;
				CarryOut <= 0;
			end
			5'b01111:
			begin
				Sum <= 2'b00;
				CarryOut <= 1;
			end

			5'b10000:
			begin
				Sum <= 2'b10;
				CarryOut <= 0;
			end
			5'b10001:
			begin
				Sum <= 2'b01;
				CarryOut <= 0;
			end
			5'b10010:
			begin
				Sum <= 2'b01;
				CarryOut <= 0;
			end
			5'b10011:
			begin
				Sum <= 2'b11;
				CarryOut <= 0;
			end
			5'b10100:
			begin
				Sum <= 2'b01;
				CarryOut <= 0;
			end
			5'b10101:
			begin
				Sum <= 2'b11;
				CarryOut <= 0;
			end
			5'b10110:
			begin
				Sum <= 2'b11;
				CarryOut <= 0;
			end
			5'b10111:
			begin
				Sum <= 2'b00;
				CarryOut <= 1;
			end

			5'b11000:
			begin
				Sum <= 2'b01;
				CarryOut <= 0;
			end
			5'b11001:
			begin
				Sum <= 2'b11;
				CarryOut <= 0;
			end
			5'b11010:
			begin
				Sum <= 2'b11;
				CarryOut <= 0;
			end
			5'b11011:
			begin
				Sum <= 2'b00;
				CarryOut <= 1;
			end
			5'b11100:
			begin
				Sum <= 2'b11;
				CarryOut <= 0;
			end
			5'b11101:
			begin
				Sum <= 2'b00;
				CarryOut <= 1;
			end
			5'b11110:
			begin
				Sum <= 2'b00;
				CarryOut <= 1;
			end
			5'b11111:
			begin
				Sum <= 2'b10;
				CarryOut <= 1;
			end
		endcase
	end
endmodule*/

module twobitFullAdder (A, B, CarryIn, Sum, CarryOut);

	input [1:0]A;
	input [1:0]B;
	input CarryIn;

	output [1:0]Sum;
	output CarryOut;

	wire carry;

	onebitadder add1(A[0], B[0], CarryIn, Sum[0], carry);
	onebitadder add2(A[1], B[1], carry, Sum[1], CarryOut);


endmodule

Combinational Circuits/Adder/Full Adder/2bitadder/2bitFullAdderTB.v
module twobitFullAdderTB ();

	reg [1:0] A;
	reg [1:0] B;
	reg CarryIn;
	wire [1:0] Sum;
	wire CarryOut;


	twobitFullAdder DUT (.A(A) , .B(B), .CarryIn(CarryIn), .Sum(Sum), .CarryOut(CarryOut));

	task init;
	 	begin
			A = 0;
			B = 0;
			CarryIn = 0;
		end
	endtask

	initial
	begin
 		$monitor ($time, "  A = %b , B = %b , CarryIn = %b, Result = %b%b",A,B,CarryIn,CarryOut,Sum);
		$dumpfile ("twobitFullAdderwaveform.vcd");
		$dumpvars(0, twobitFullAdderTB);
	end

	initial
	begin
		init;
		#0 A = 2'b11; B = 2'b11 ; CarryIn = 1;
		#5 A = 2'b01; B = 2'b11 ; CarryIn = 0;
		#5 A = 2'b11; B = 2'b11 ; CarryIn = 0;
		#5 A = 2'b01; B = 2'b10 ; CarryIn = 0;
		#5 A = 2'b10; B = 2'b00 ; CarryIn = 1;
		#5 A = 2'b01; B = 2'b10 ; CarryIn = 1;
		#5 A = 2'b00; B = 2'b00 ; CarryIn = 0;
		#5 A = 2'b10; B = 2'b11 ; CarryIn = 0;
		#5 $finish;
	end
endmodule

Combinational Circuits/Adder/Full Adder/2bitadder/twobitFullAdderwaveform.vcd
$date
	Sun Apr 12 02:25:24 2020
$end
$version
	Icarus Verilog
$end
$timescale
	1s
$end
$scope module twobitFullAdderTB $end
$var wire 1 ! CarryOut $end
$var wire 2 " Sum [1:0] $end
$var reg 2 # A [1:0] $end
$var reg 2 $ B [1:0] $end
$var reg 1 % CarryIn $end
$scope module DUT $end
$var wire 2 & A [1:0] $end
$var wire 2 ' B [1:0] $end
$var wire 1 ( CarryIn $end
$var wire 1 ! CarryOut $end
$var wire 2 ) Sum [1:0] $end
$var wire 1 * carry $end
$scope module add1 $end
$var wire 1 + A $end
$var wire 1 , B $end
$var wire 1 ( CarryIn $end
$var wire 1 * CarryOut $end
$var wire 1 - Sum $end
$var wire 1 . c1 $end
$var wire 1 / c2 $end
$var wire 1 0 s1 $end
$scope module ha1 $end
$var wire 1 + A $end
$var wire 1 , B $end
$var reg 1 1 Carry $end
$var reg 1 2 Sum $end
$upscope $end
$scope module ha2 $end
$var wire 1 0 A $end
$var wire 1 ( B $end
$var reg 1 3 Carry $end
$var reg 1 4 Sum $end
$upscope $end
$upscope $end
$scope module add2 $end
$var wire 1 5 A $end
$var wire 1 6 B $end
$var wire 1 * CarryIn $end
$var wire 1 ! CarryOut $end
$var wire 1 7 Sum $end
$var wire 1 8 c1 $end
$var wire 1 9 c2 $end
$var wire 1 : s1 $end
$scope module ha1 $end
$var wire 1 5 A $end
$var wire 1 6 B $end
$var reg 1 ; Carry $end
$var reg 1 < Sum $end
$upscope $end
$scope module ha2 $end
$var wire 1 : A $end
$var wire 1 * B $end
$var reg 1 = Carry $end
$var reg 1 > Sum $end
$upscope $end
$upscope $end
$upscope $end
$scope task init $end
$upscope $end
$upscope $end
$enddefinitions $end
#0
$dumpvars
1>
0=
0<
1;
0:
09
18
17
16
15
14
03
02
11
00
0/
1.
1-
1,
1+
1*
b11 )
1(
b11 '
b11 &
1%
b11 $
b11 #
b11 "
1!
$end
#5
1=
19
0>
07
1!
0;
08
1<
1:
04
0-
b0 "
b0 )
05
0%
0(
b1 #
b1 &
#10
0=
09
1>
17
b10 "
b10 )
1;
18
0<
0:
15
b11 #
b11 &
#15
14
1-
0=
09
1>
17
b11 "
b11 )
0*
0!
01
0.
12
10
0;
08
1<
1:
0,
05
b10 $
b10 '
b1 #
b1 &
#20
0!
0=
09
1>
17
0*
02
00
03
0/
14
1-
b11 "
b11 )
06
0+
15
1%
1(
b0 $
b0 '
b10 #
b10 &
#25
1!
1=
19
0>
07
1*
13
1/
04
0-
b0 "
b0 )
12
10
16
1+
05
b10 $
b10 '
b1 #
b1 &
#30
0!
0=
09
0*
0<
0:
02
00
03
0/
04
0-
b0 "
b0 )
06
0+
0%
0(
b0 $
b0 '
b0 #
b0 &
#35
14
1-
b1 "
b1 )
1!
12
10
1;
18
1,
16
15
b11 $
b11 '
b10 #
b10 &
