Sequential/Latches/SRLatch/1bitSRlatch.v
module onebitSRlatch (Set , Reset, En, Q, Qbar);

 input Set;
 input Reset;
 input En;
 
 output reg Q;
 output wire Qbar; 
 

 assign Qbar = ~Q;
	always @(*)
	begin
		if ((!En)||(Set == 0 && Reset == 0))
		begin
			Q = Q;
		end
		else if(En)
		begin
			if(Set != Reset)
			begin
				Q = Set;
			end
			else
			begin
				Q = 1'bx;
			end
		end
	end
endmodule

Sequential/Latches/SRLatch/4bitSRlatch.v
module fourbitSRlatch (Set , Reset, En, Q, Qbar);

 input [3:0]Set;
 input [3:0]Reset;
 input En;

 output [3:0]Q;
 output [3:0]Qbar;
 
 	onebitSRlatch Sr1 (Set[0], Reset [0], En, Q[0], Qbar[0]);
 	onebitSRlatch Sr2 (Set[1], Reset [1], En, Q[1], Qbar[1]);
 	onebitSRlatch Sr3 (Set[2], Reset [2], En, Q[2], Qbar[2]);
 	onebitSRlatch Sr4 (Set[3], Reset [3], En, Q[3], Qbar[3]);

endmodule

Sequential/Latches/SRLatch/4bitSRlatchTB.v
module fourbitSRlatchTB ();
 reg [3:0]Set;
 reg [3:0]Reset;
 reg En;
 
 wire [3:0]Q;
 wire [3:0]Qbar;

 integer i;

 	fourbitSRlatch DUT (.Set(Set), .Reset(Reset), .En(En), .Q(Q), .Qbar(Qbar));
	
	initial
	begin
		$monitor ($time,"  Set = %b, Reset = %b, En = %b, Q = %b, Qbar = %b", Set,Reset,En,Q,Qbar);
		$dumpfile("fourbitSRlatchwaveform.vcd");
		$dumpvars(0, fourbitSRlatchTB);
	end

	task initialize;
		begin
			Set = 0;
			Reset = 0;
			En = 1;
		end
	endtask

	initial
	begin 
		initialize;
	        #5 Set = 4'b0000; Reset = 4'b1111; En = 1;
		#5 Set = 4'b0000; Reset = 4'b0000; En = 1;

 		#5 Set = 4'b0101; Reset = 4'b1010; En = 1;
		#5 Set = 4'b1100; Reset = 4'b0000; En = 0;

  		#5 Set = 4'b1111; Reset = 4'b0000; En = 1;
		#5 Set = 4'b1100; Reset = 4'b0011; En = 1;

	  	#5 Set = 4'b1100; Reset = 4'b0011; En = 1;
  		#5 Set = 4'b1010; Reset = 4'b0101; En = 1;
		#5 $finish;
	end
endmodule

Sequential/Latches/SRLatch/fourbitSRlatchwaveform.vcd
$date
	Thu Apr 30 23:29:16 2020
$end
$version
	Icarus Verilog
$end
$timescale
	1s
$end
$scope module fourbitSRlatchTB $end
$var wire 4 ! Q [3:0] $end
$var wire 4 " Qbar [3:0] $end
$var reg 1 # En $end
$var reg 4 $ Reset [3:0] $end
$var reg 4 % Set [3:0] $end
$scope module DUT $end
$var wire 1 & En $end
$var wire 4 ' Q [3:0] $end
$var wire 4 ( Qbar [3:0] $end
$var wire 4 ) Reset [3:0] $end
$var wire 4 * Set [3:0] $end
$scope module Sr1 $end
$var wire 1 & En $end
$var wire 1 + Qbar $end
$var wire 1 , Reset $end
$var wire 1 - Set $end
$var reg 1 . Q $end
$upscope $end
$scope module Sr2 $end
$var wire 1 & En $end
$var wire 1 / Qbar $end
$var wire 1 0 Reset $end
$var wire 1 1 Set $end
$var reg 1 2 Q $end
$upscope $end
$scope module Sr3 $end
$var wire 1 & En $end
$var wire 1 3 Qbar $end
$var wire 1 4 Reset $end
$var wire 1 5 Set $end
$var reg 1 6 Q $end
$upscope $end
$scope module Sr4 $end
$var wire 1 & En $end
$var wire 1 7 Qbar $end
$var wire 1 8 Reset $end
$var wire 1 9 Set $end
$var reg 1 : Q $end
$upscope $end
$upscope $end
$scope task initialize $end
$upscope $end
$upscope $end
$enddefinitions $end
#0
$dumpvars
x:
09
08
x7
x6
05
04
x3
x2
01
00
x/
x.
0-
0,
x+
b0 *
b0 )
bx (
bx '
1&
b0 %
b0 $
1#
bx "
bx !
$end
#5
1+
1/
13
17
b1111 "
b1111 (
0.
02
06
0:
b0 !
b0 '
1,
10
14
18
b1111 $
b1111 )
#10
0,
00
04
08
b0 $
b0 )
#15
0+
03
b1010 "
b1010 (
1.
16
b101 !
b101 '
10
18
1-
15
b1010 $
b1010 )
b101 %
b101 *
#20
00
08
0-
19
0#
0&
b0 $
b0 )
b1100 %
b1100 *
#25
07
0/
b0 "
b0 (
1:
12
b1111 !
b1111 '
1-
11
1#
1&
b1111 %
b1111 *
#30
1+
1/
b11 "
b11 (
0.
02
b1100 !
b1100 '
1,
10
0-
01
b11 $
b11 )
b1100 %
b1100 *
#40
0/
13
b101 "
b101 (
12
06
b1010 !
b1010 '
00
14
11
05
b101 $
b101 )
b1010 %
b1010 *
